biomaj_cron/__init__.py
biomaj_cron/biomaj_cron_web.py
biomaj_cron/cron.py
biomaj_cron-3.0.4.data/scripts/biomaj_load_cron.py
biomaj_cron-3.0.4.dist-info/LICENSE
biomaj_cron-3.0.4.dist-info/METADATA
biomaj_cron-3.0.4.dist-info/WHEEL
biomaj_cron-3.0.4.dist-info/top_level.txt
biomaj_cron-3.0.4.dist-info/RECORD
